LICENSE
MANIFEST.in
README
setup.py
translocation/__init__.py
translocation/__main__.py
translocation/source.py
translocation.egg-info/PKG-INFO
translocation.egg-info/SOURCES.txt
translocation.egg-info/dependency_links.txt
translocation.egg-info/not-zip-safe
translocation.egg-info/top_level.txt