Metadata-Version: 2.4
Name: translocation
Version: 0.3
Summary: Correction of translocation defects in crystals
Home-page: https://github.com/kolenpe1/translocation
Author: Petr Kolenko
Author-email: kolenpe1@cvut.cz
Classifier: Intended Audience :: Developers
Classifier: Programming Language :: Python
Classifier: Programming Language :: Python :: 3
Classifier: Topic :: Software Development
License-File: LICENSE
Dynamic: author
Dynamic: author-email
Dynamic: classifier
Dynamic: description
Dynamic: home-page
Dynamic: license-file
Dynamic: summary
